purdue_af_shutdown_button/__init__.py
purdue_af_shutdown_button/_version.py
purdue_af_shutdown_button-0.1.0.data/data/share/jupyter/labextensions/purdue-af-shutdown-button/package.json
purdue_af_shutdown_button-0.1.0.data/data/share/jupyter/labextensions/purdue-af-shutdown-button/static/736.bef249f8d35253354de9.js
purdue_af_shutdown_button-0.1.0.data/data/share/jupyter/labextensions/purdue-af-shutdown-button/static/964.682c4185b871a7f7c841.js
purdue_af_shutdown_button-0.1.0.data/data/share/jupyter/labextensions/purdue-af-shutdown-button/static/remoteEntry.41a875cee769200fe1e5.js
purdue_af_shutdown_button-0.1.0.data/data/share/jupyter/labextensions/purdue-af-shutdown-button/static/style.js
purdue_af_shutdown_button-0.1.0.data/data/share/jupyter/labextensions/purdue-af-shutdown-button/static/third-party-licenses.json
purdue_af_shutdown_button-0.1.0.data/data/share/jupyter/labextensions/purdue-af-shutdown-button/install.json
purdue_af_shutdown_button-0.1.0.dist-info/METADATA
purdue_af_shutdown_button-0.1.0.dist-info/WHEEL
purdue_af_shutdown_button-0.1.0.dist-info/licenses/LICENSE
purdue_af_shutdown_button-0.1.0.dist-info/RECORD
